adarnauth_esi-1.4.7.dist-info/METADATA
adarnauth_esi-1.4.7.dist-info/RECORD
adarnauth_esi-1.4.7.dist-info/WHEEL
adarnauth_esi-1.4.7.dist-info/top_level.txt
esi/__init__.py
esi/admin.py
esi/app_settings.py
esi/apps.py
esi/checks.py
esi/clients.py
esi/decorators.py
esi/errors.py
esi/managers.py
esi/models.py
esi/tasks.py
esi/urls.py
esi/views.py
esi/migrations/0001_initial.py
esi/migrations/0002_scopes_20161208.py
esi/migrations/0003_hide_tokens_from_admin_site.py
esi/migrations/0004_remove_unique_access_token.py
esi/migrations/__init__.py
esi/static/esi/img/EVE_SSO_Login_Buttons_Large_Black.png
esi/static/esi/img/EVE_SSO_Login_Buttons_Large_White.png
esi/static/esi/img/EVE_SSO_Login_Buttons_Small_Black.png
esi/static/esi/img/EVE_SSO_Login_Buttons_Small_White.png
esi/templates/esi/select_token.html
