Metadata-Version: 2.1
Name: adarnauth-esi
Version: 1.4.7
Summary: Django app for accessing the EVE Swagger Interface.
Home-page: https://github.com/adarnof/adarnauth-esi
Author: Adarnof
Author-email: adarnof@gmail.com
License: GNU General Public License v3 (GPLv3)
Platform: UNKNOWN
Classifier: Environment :: Web Environment
Classifier: Framework :: Django
Classifier: Framework :: Django :: 1.10
Classifier: Framework :: Django :: 1.11
Classifier: Framework :: Django :: 2.0
Classifier: Intended Audience :: Developers
Classifier: License :: OSI Approved :: GNU General Public License v3 (GPLv3)
Classifier: Operating System :: OS Independent
Classifier: Programming Language :: Python
Classifier: Programming Language :: Python :: 2
Classifier: Programming Language :: Python :: 2.7
Classifier: Programming Language :: Python :: 3
Classifier: Programming Language :: Python :: 3.4
Classifier: Programming Language :: Python :: 3.5
Classifier: Programming Language :: Python :: 3.6
Classifier: Topic :: Internet :: WWW/HTTP
Classifier: Topic :: Internet :: WWW/HTTP :: Dynamic Content
Requires-Dist: requests (<3.0,>=2.9.1)
Requires-Dist: requests-oauthlib (<1.0,>=0.8.0)
Requires-Dist: django (>=1.10)
Requires-Dist: bravado (<10.0,>=8.4.0)
Requires-Dist: celery (>=4.0.2)
